ansible_sphinx/__init__.py
ansible_sphinx/ansible.py
ansible_sphinx/version.py
ansible_sphinx-0.0.1.dist-info/AUTHORS
ansible_sphinx-0.0.1.dist-info/LICENSE
ansible_sphinx-0.0.1.dist-info/METADATA
ansible_sphinx-0.0.1.dist-info/WHEEL
ansible_sphinx-0.0.1.dist-info/pbr.json
ansible_sphinx-0.0.1.dist-info/top_level.txt
ansible_sphinx-0.0.1.dist-info/RECORD
