Metadata-Version: 2.1
Name: ansible-sphinx
Version: 0.0.1
Summary: A Sphinx extension for documenting Ansible roles and playbooks
Home-page: https://github.com/osism/ansible-sphinx
Author: OSISM GmbH
Author-email: info@osism.tech
License: UNKNOWN
Platform: UNKNOWN
Classifier: Intended Audience :: Information Technology
Classifier: Intended Audience :: System Administrators
Classifier: License :: OSI Approved :: Apache Software License
Classifier: Operating System :: POSIX :: Linux
Classifier: Programming Language :: Python
Classifier: Programming Language :: Python :: 3
License-File: LICENSE
License-File: AUTHORS
Requires-Dist: pbr (>=1.1.0)
Requires-Dist: sphinx (>=1.5.1)
Requires-Dist: pyyaml
